django_mathtext/.env.sample
django_mathtext/app/__init__.py
django_mathtext/app/admin.py
django_mathtext/app/apps.py
django_mathtext/app/models.py
django_mathtext/app/tests.py
django_mathtext/app/urls.py
django_mathtext/app/views.py
django_mathtext/django_mathtext/__init__.py
django_mathtext/django_mathtext/asgi.py
django_mathtext/django_mathtext/constants.py
django_mathtext/django_mathtext/settings.py
django_mathtext/django_mathtext/urls.py
django_mathtext/django_mathtext/wsgi.py
django_mathtext/manage.py
django_mathtext/static/styles.css
django_mathtext/templates/home.html
django_mathtext/tests/__init__.py
django_mathtext/tests/test_text2int.py
django_mathtext-0.0.1.dist-info/METADATA
django_mathtext-0.0.1.dist-info/WHEEL
django_mathtext-0.0.1.dist-info/RECORD
