Metadata-Version: 2.1
Name: django-mathtext
Version: 0.0.1
Summary: Natural Language Understanding (text processing) for math symbols, digits, and words with a Gradio user interface and REST API.
License: AGPL-3.0-or-later
Author: Sebastian Larsen
Author-email: sebastianlarson22@gmail.com
Requires-Python: >=3.8,<4.0
Classifier: License :: OSI Approved :: GNU Affero General Public License v3 or later (AGPLv3+)
Classifier: Operating System :: OS Independent
Classifier: Programming Language :: Python :: 3
Classifier: Programming Language :: Python :: 3.8
Classifier: Programming Language :: Python :: 3.9
Classifier: Programming Language :: Python :: 3.10
Classifier: Programming Language :: Python :: 3.11
Classifier: Programming Language :: Python :: 3
Classifier: Programming Language :: Python :: 3.8
Classifier: Programming Language :: Python :: 3.9
Requires-Dist: dill (>=0.3.6,<0.4.0)
Requires-Dist: django-mathactive (>=0.0.1,<0.0.2)
Requires-Dist: fastapi (>=0.90.0,<0.91.0)
Requires-Dist: fuzzywuzzy (>=0.18.0,<0.19.0)
Requires-Dist: pandas (>=1.5.3,<2.0.0)
Requires-Dist: pydantic
Requires-Dist: requests (>=2.27.0,<2.28.0)
Requires-Dist: scipy (>=1.10.1,<2.0.0)
Requires-Dist: sentence-transformers (>=2.2.2,<3.0.0)
Requires-Dist: sentencepiece (>=0.1.0,<0.2.0)
Requires-Dist: sentry_sdk (>=1.19.1,<2.0.0)
Requires-Dist: supabase
Requires-Dist: toml (>=0.10.2,<0.11.0)
Requires-Dist: uvicorn (>=0.17.0,<0.18.0)
